Workbook

Sheet Data
A1: Data | B1: Source values and formulas
A3: Balance Sheet Inputs | B3: Amount | C3: Key Ratios | D3: Formula Result
A4: Current Assets | B4: 0
A5: Non-current Assets | B5: 0
A6: Total Assets | B6: =SUM(B4:B5)
A7: Current Liabilities | B7: 0
A8: Non-current Liabilities | B8: 0
A9: Total Liabilities | B9: =SUM(B7:B8)
A10: Equity | B10: 0
A11: Check: Liabilities + Equity | B11: =B9+B10
A13: Income Statement Inputs | B13: Amount | C13: Ratio | D13: Formula Result
A14: Revenue | B14: 0
A15: Net Income | B15: 0
A17: ROE Analysis | B17: Amount | C17: Ratio | D17: Formula Result
A18: ROE | C18: ROE | D18: =IF(B10=0,"",B15/B10)
A19: ROA | C19: ROA | D19: =IF(B6=0,"",B15/B6)
A20: Net Profit Margin | C20: Net Profit Margin | D20: =IF(B14=0,"",B15/B14)
A21: Current Ratio | C21: Current Ratio | D21: =IF(B7=0,"",B4/B7)
A22: Debt Ratio | C22: Debt Ratio | D22: =IF(B6=0,"",B9/B6)
A23: Debt to Equity | C23: Debt to Equity | D23: =IF(B10=0,"",B9/B10)
A24: Asset Turnover | C24: Asset Turnover | D24: =IF(B6=0,"",B14/B6)
A25: Equity Multiplier | C25: Equity Multiplier | D25: =IF(B10=0,"",B6/B10)
A26: DuPont Check | C26: ROE via DuPont | D26: =E20*E24*E25

Sheet English
A1: Financial Statement Analysis Template | B1: Both language sheets are linked to the same hidden Data sheet and stay synchronized.
A3: Balance Sheet Inputs | B3: Amount | C3: Key Ratios | D3: Formula Result
A4: Current Assets | B4: ='Data'!B4
A5: Non-current Assets | B5: ='Data'!B5
A6: Total Assets | B6: ='Data'!B6
A7: Current Liabilities | B7: ='Data'!B7
A8: Non-current Liabilities | B8: ='Data'!B8
A9: Total Liabilities | B9: ='Data'!B9
A10: Equity | B10: ='Data'!B10
A11: Check: Liabilities + Equity | B11: ='Data'!B11
A13: Income Statement Inputs | B13: Amount | C13: Ratio | D13: Formula Result
A14: Revenue | B14: ='Data'!B14
A15: Net Income | B15: ='Data'!B15
A17: ROE Analysis | B17: Amount | C17: Ratio | D17: Formula Result
A18: ROE | B18: ='Data'!B18 | C18: ROE | D18: ='Data'!E18
A19: ROA | B19: ='Data'!B19 | C19: ROA | D19: ='Data'!E19
A20: Net Profit Margin | B20: ='Data'!B20 | C20: Net Profit Margin | D20: ='Data'!E20
A21: Current Ratio | B21: ='Data'!B21 | C21: Current Ratio | D21: ='Data'!E21
A22: Debt Ratio | B22: ='Data'!B22 | C22: Debt Ratio | D22: ='Data'!E22
A23: Debt to Equity | B23: ='Data'!B23 | C23: Debt to Equity | D23: ='Data'!E23
A24: Asset Turnover | B24: ='Data'!B24 | C24: Asset Turnover | D24: ='Data'!E24
A25: Equity Multiplier | B25: ='Data'!B25 | C25: Equity Multiplier | D25: ='Data'!E25
A26: DuPont Check | B26: ='Data'!B26 | C26: ROE via DuPont | D26: ='Data'!E26

Sheet Japanese
A1: 財務諸表分析テンプレート | B1: 両方の言語シートは同じ非表示のDataシートに連動し、数値と結果が同期されます。
A3: 貸借対照表入力 | B3: 金額 | C3: 主要指標 | D3: 計算結果
A4: 流動資産 | B4: ='Data'!B4
A5: 固定資産 | B5: ='Data'!B5
A6: 総資産 | B6: ='Data'!B6
A7: 流動負債 | B7: ='Data'!B7
A8: 固定負債 | B8: ='Data'!B8
A9: 総負債 | B9: ='Data'!B9
A10: 自己資本 | B10: ='Data'!B10
A11: 確認: 負債 + 自己資本 | B11: ='Data'!B11
A13: 損益計算書入力 | B13: 金額 | C13: 指標 | D13: 計算結果
A14: 売上高 | B14: ='Data'!B14
A15: 当期純利益 | B15: ='Data'!B15
A17: ROE分析 | B17: 金額 | C17: 指標 | D17: 計算結果
A18: ROE | B18: ='Data'!B18 | C18: ROE | D18: ='Data'!E18
A19: ROA | B19: ='Data'!B19 | C19: ROA | D19: ='Data'!E19
A20: 売上高純利益率 | B20: ='Data'!B20 | C20: 売上高純利益率 | D20: ='Data'!E20
A21: 流動比率 | B21: ='Data'!B21 | C21: 流動比率 | D21: ='Data'!E21
A22: 負債比率 | B22: ='Data'!B22 | C22: 負債比率 | D22: ='Data'!E22
A23: D/Eレシオ | B23: ='Data'!B23 | C23: D/Eレシオ | D23: ='Data'!E23
A24: 総資産回転率 | B24: ='Data'!B24 | C24: 総資産回転率 | D24: ='Data'!E24
A25: 財務レバレッジ | B25: ='Data'!B25 | C25: 財務レバレッジ | D25: ='Data'!E25
A26: デュポン確認 | B26: ='Data'!B26 | C26: デュポン式ROE | D26: ='Data'!E26
